fvirt/__init__.py
fvirt/cli.py
fvirt/commands/__init__.py
fvirt/commands/_base/autostart.py
fvirt/commands/_base/command.py
fvirt/commands/_base/config.py
fvirt/commands/_base/exitcode.py
fvirt/commands/_base/filetransfer.py
fvirt/commands/_base/group.py
fvirt/commands/_base/help.py
fvirt/commands/_base/info.py
fvirt/commands/_base/lifecycle.py
fvirt/commands/_base/list.py
fvirt/commands/_base/match.py
fvirt/commands/_base/new.py
fvirt/commands/_base/objects.py
fvirt/commands/_base/state.py
fvirt/commands/_base/tables.py
fvirt/commands/_base/terminal.py
fvirt/commands/_base/xml.py
fvirt/commands/_base/xslt.py
fvirt/commands/config/__init__.py
fvirt/commands/config/dump.py
fvirt/commands/config/effective.py
fvirt/commands/config/paths.py
fvirt/commands/domain/__init__.py
fvirt/commands/domain/_mixin.py
fvirt/commands/domain/autostart.py
fvirt/commands/domain/console.py
fvirt/commands/domain/info.py
fvirt/commands/domain/list.py
fvirt/commands/domain/new.py
fvirt/commands/domain/reset.py
fvirt/commands/domain/save.py
fvirt/commands/domain/shutdown.py
fvirt/commands/domain/start.py
fvirt/commands/domain/stop.py
fvirt/commands/domain/undefine.py
fvirt/commands/domain/xml.py
fvirt/commands/domain/xslt.py
fvirt/commands/host/__init__.py
fvirt/commands/host/info.py
fvirt/commands/host/uri.py
fvirt/commands/host/version.py
fvirt/commands/pool/__init__.py
fvirt/commands/pool/_mixin.py
fvirt/commands/pool/autostart.py
fvirt/commands/pool/build.py
fvirt/commands/pool/delete.py
fvirt/commands/pool/info.py
fvirt/commands/pool/list.py
fvirt/commands/pool/new.py
fvirt/commands/pool/refresh.py
fvirt/commands/pool/start.py
fvirt/commands/pool/stop.py
fvirt/commands/pool/undefine.py
fvirt/commands/pool/xml.py
fvirt/commands/pool/xslt.py
fvirt/commands/schema.py
fvirt/commands/version.py
fvirt/commands/volume/__init__.py
fvirt/commands/volume/_mixin.py
fvirt/commands/volume/delete.py
fvirt/commands/volume/download.py
fvirt/commands/volume/info.py
fvirt/commands/volume/list.py
fvirt-0.1.1.dist-info/LICENSE.md
fvirt-0.1.1.dist-info/METADATA
fvirt-0.1.1.dist-info/WHEEL
fvirt-0.1.1.dist-info/entry_points.txt
fvirt-0.1.1.dist-info/RECORD
