Metadata-Version: 2.1
Name: fvirt
Version: 0.1.1
Summary: A CLI frontend for libvirt.
Home-page: https://github.com/Ferroin/fvirt
License: MITNFA
Author: Austin S. Hemmelgarn
Author-email: ahferroin7@gmail.com
Requires-Python: >=3.11,<4.0
Classifier: Development Status :: 3 - Alpha
Classifier: Environment :: Console
Classifier: License :: Other/Proprietary License
Classifier: Programming Language :: Python :: 3
Classifier: Programming Language :: Python :: 3.11
Classifier: Programming Language :: Python :: 3.12
Requires-Dist: blessed (>=1.20.0,<2.0.0)
Requires-Dist: click (>=8.1.7,<9.0.0)
Requires-Dist: frozendict (>=2.3.10,<3.0.0)
Requires-Dist: jinja2 (>=3.1.2,<4.0.0)
Requires-Dist: libvirt-python (>=9.10.0,<10.0.0)
Requires-Dist: lxml (>=4.9.4,<6.0.0)
Requires-Dist: platformdirs (>=4.1.0,<5.0.0)
Requires-Dist: psutil (>=5.9.7,<6.0.0)
Requires-Dist: pydantic (>=2.5.3,<3.0.0)
Requires-Dist: pydantic-extra-types (>=2.2.0,<3.0.0)
Requires-Dist: ruamel-yaml (>=0.18.5,<0.19.0)
Project-URL: Repository, https://github.com/Ferroin/fvirt
